apache_airflow_granulate_databricks_auto_patch/__init__.py
apache_airflow_granulate_databricks_auto_patch-0.1.0.dist-info/LICENSE
apache_airflow_granulate_databricks_auto_patch-0.1.0.dist-info/METADATA
apache_airflow_granulate_databricks_auto_patch-0.1.0.dist-info/WHEEL
apache_airflow_granulate_databricks_auto_patch-0.1.0.dist-info/RECORD
